par_sieve-1.5.0.dist-info/METADATA
par_sieve-1.5.0.dist-info/WHEEL
par_sieve-1.5.0.dist-info/licenses/LICENSE
par_sieve/__init__.py
par_sieve/par_sieve.cpython-313t-s390x-linux-gnu.so
par_sieve-1.5.0.dist-info/RECORD
