Metadata-Version: 2.4
Name: par-sieve
Version: 1.5.0
Classifier: Programming Language :: Rust
Classifier: Programming Language :: Python :: Implementation :: CPython
Classifier: Programming Language :: Python :: Implementation :: PyPy
Requires-Dist: numpy
License-File: LICENSE
Summary: Parallel Prime Sieve for Python
Author-email: Sam Foster <slfotg@gmail.com>
Requires-Python: >=3.8
Project-URL: Homepage, https://github.com/slfotg/par-sieve
